qosst/__init__.py
qosst/code_quality.py
qosst-0.10.0.dist-info/METADATA
qosst-0.10.0.dist-info/WHEEL
qosst-0.10.0.dist-info/entry_points.txt
qosst-0.10.0.dist-info/RECORD
